flask_simplerest
