Metadata-Version: 1.0
Name: flask-simplerest
Version: 1.0.3
Summary: A Flask extension for easy ReSTful API generation
Home-page: https://github.com/unk2k/flask_simplerest
Author: Constantin Slednev
Author-email: c.slednev@gmail.com
License: BSD
Platform: any
Classifier: Development Status :: 5 - Production/Stable
Classifier: Intended Audience :: Developers
Classifier: License :: OSI Approved :: BSD License
Classifier: Operating System :: OS Independent
Classifier: Programming Language :: Python
Classifier: Framework :: Flask
